jaxkuramoto/__init__.py
jaxkuramoto/kuramoto.py
jaxkuramoto/ode.py
jaxkuramoto/solution.py
jaxkuramoto/distribution/__init__.py
jaxkuramoto/distribution/base.py
jaxkuramoto/distribution/cauchy.py
jaxkuramoto/distribution/cauchy_multiply.py
jaxkuramoto/distribution/cauchy_sum.py
jaxkuramoto/distribution/finite_differential.py
jaxkuramoto/distribution/general_cauchy.py
jaxkuramoto/distribution/general_normal.py
jaxkuramoto/distribution/normal.py
jaxkuramoto/distribution/uniform.py
jaxkuramoto/solver/__init__.py
jaxkuramoto/solver/fixed_point.py
jaxkuramoto/solver/integral.py
jaxkuramoto/solver/ode_solver.py
jaxkuramoto/solver/sde_solver.py
jaxkuramoto/theory/__init__.py
jaxkuramoto/theory/critical_point.py
jaxkuramoto/theory/ott_antonsen.py
jaxkuramoto/theory/self_consistent.py
jaxkuramoto-0.0.8.dist-info/LICENSE
jaxkuramoto-0.0.8.dist-info/METADATA
jaxkuramoto-0.0.8.dist-info/WHEEL
jaxkuramoto-0.0.8.dist-info/top_level.txt
jaxkuramoto-0.0.8.dist-info/RECORD
