Metadata-Version: 2.1
Name: jaxkuramoto
Version: 0.0.8
Summary: JAX implementation of Kuramoto model.
Home-page: https://github.com/yonesuke/jaxkuramoto
Author: Ryosuke Yoneda
Author-email: 13e.e.c.13@gmail.com
Classifier: Programming Language :: Python :: 3
Classifier: License :: OSI Approved :: MIT License
Classifier: Operating System :: OS Independent
Requires-Python: >=3.7
License-File: LICENSE
Requires-Dist: jax
